maileasy/__init__.py
maileasy/functions.py
maileasy-0.0.2.dist-info/METADATA
maileasy-0.0.2.dist-info/RECORD
maileasy-0.0.2.dist-info/WHEEL
maileasy-0.0.2.dist-info/top_level.txt
