Metadata-Version: 2.1
Name: maileasy
Version: 0.0.2
Summary: Simple mail sending
Home-page: https://github.com/ctrl-q/maileasy
Author: ctrl-q
Author-email: 
License: GPLv3
Platform: UNKNOWN
Classifier: License :: OSI Approved :: GNU General Public License v3 (GPLv3)
Classifier: Programming Language :: Python
Classifier: Programming Language :: Python :: 3
Classifier: Programming Language :: Python :: 3.6
Classifier: Programming Language :: Python :: Implementation :: CPython
Classifier: Programming Language :: Python :: Implementation :: PyPy
Requires-Python: >=3.0.0
Requires-Dist: gnupg
